nci_ipynb/__init__.py
nci_ipynb-2023.11.0.3.dist-info/LICENSE
nci_ipynb-2023.11.0.3.dist-info/METADATA
nci_ipynb-2023.11.0.3.dist-info/WHEEL
nci_ipynb-2023.11.0.3.dist-info/top_level.txt
nci_ipynb-2023.11.0.3.dist-info/RECORD
