Metadata-Version: 2.1
Name: nci-ipynb
Version: 2023.11.0.3
Summary: Simply returns either notebook filename or the full path to the notebook when run from Jupyter notebook in browser.
Home-page: https://github.com/nci/nci_ipynb
Author: Edison Guo
Author-email: edison.guo@anu.edu.au
License: MIT
Keywords: jupyter,notebook,filename
Classifier: Operating System :: OS Independent
Classifier: Development Status :: 4 - Beta
Classifier: Framework :: Jupyter
Classifier: Topic :: Utilities
Classifier: License :: OSI Approved :: MIT License
Requires-Python: >=3.4
License-File: LICENSE
Requires-Dist: ipykernel
